occuprob/__init__.py
occuprob/_version.py
occuprob/cli.py
occuprob/io.py
occuprob/partitionfunctions.py
occuprob/superpositions.py
occuprob/utils.py
occuprob/data/README.md
occuprob/data/look_and_say.dat
occuprob/data/test.xyz
occuprob/tests/__init__.py
occuprob/tests/test_io.py
occuprob/tests/test_occuprob.py
occuprob/tests/test_partitionfunctions.py
occuprob/tests/test_superpositions.py
occuprob/tests/test_utils.py
occuprob-0.1.0.dist-info/LICENSE
occuprob-0.1.0.dist-info/METADATA
occuprob-0.1.0.dist-info/WHEEL
occuprob-0.1.0.dist-info/entry_points.txt
occuprob-0.1.0.dist-info/top_level.txt
occuprob-0.1.0.dist-info/RECORD
