Metadata-Version: 2.1
Name: occuprob
Version: 0.1.0
Summary: A tool for calculating occupation probabilities and ensemble-averaged properties via the superposition approximation.
Author: Luis Galvez
Author-email: luisegalvezg@gmail.com
License: MIT
Platform: Linux
Platform: Mac OS-X
Platform: Unix
Requires-Python: >=3.7
License-File: LICENSE
Requires-Dist: numpy (>=1.19.0)
Requires-Dist: ase (>=3.22.1)
Requires-Dist: pymatgen (>=2022.0.17)
Requires-Dist: matplotlib (>=3.1.3)
